Metadata-Version: 2.1
Name: odoo11-addon-account-financial-report
Version: 11.0.2.5.2
Summary: OCA Financial Reports
Home-page: https://odoo-community.org/
Author: Camptocamp SA,initOS GmbH,redCOR AG,Eficent,Odoo Community Association (OCA)
Author-email: support@odoo-community.org
License: AGPL-3
Platform: UNKNOWN
Classifier: Programming Language :: Python
Classifier: Framework :: Odoo
Classifier: License :: OSI Approved :: GNU Affero General Public License v3
Requires-Python: >=2.7, !=3.0.*, !=3.1.*, !=3.2.*, !=3.3.*, !=3.4.*
Requires-Dist: odoo11-addon-date-range
Requires-Dist: odoo11-addon-report-xlsx
Requires-Dist: odoo (<11.1dev,>=11.0a)
